channelpack/__init__.py
channelpack/datautils.py
channelpack/dbf.py
channelpack/pack.py
channelpack/readtext.py
channelpack/readxl.py
channelpack/xlrd/__init__.py
channelpack/xlrd/biffh.py
channelpack/xlrd/book.py
channelpack/xlrd/compdoc.py
channelpack/xlrd/formatting.py
channelpack/xlrd/formula.py
channelpack/xlrd/sheet.py
channelpack/xlrd/timemachine.py
channelpack/xlrd/xldate.py
channelpack/xlrd/xlsx.py
channelpack-0.7.0.dist-info/LICENSE.txt
channelpack-0.7.0.dist-info/METADATA
channelpack-0.7.0.dist-info/WHEEL
channelpack-0.7.0.dist-info/top_level.txt
channelpack-0.7.0.dist-info/RECORD
