Metadata-Version: 2.1
Name: channelpack
Version: 0.7.0
Summary: Callable container of Numpy arrays with support for masking and slicing
Home-page: https://github.com/tomnor/channelpack
Author: Tomas Nordin
Author-email: tomnor@posteo.net
License: GPLv3+
Keywords: data-mining datafile daq masking conditions evaluation ad-hoc
Platform: UNKNOWN
Classifier: Development Status :: 3 - Alpha
Classifier: Intended Audience :: Developers
Classifier: Intended Audience :: Science/Research
Classifier: Topic :: Scientific/Engineering
Classifier: Operating System :: OS Independent
Classifier: License :: OSI Approved :: GNU General Public License v3 or later (GPLv3+)
Classifier: Programming Language :: Python :: 2
Classifier: Programming Language :: Python :: 3
